pynts/__init__.py
pynts/dataio.py
pynts/util.py
pynts/visualization.py
pynts-0.0.2a1.data/scripts/runpynts
pynts-0.0.2a1.dist-info/DESCRIPTION.rst
pynts-0.0.2a1.dist-info/METADATA
pynts-0.0.2a1.dist-info/RECORD
pynts-0.0.2a1.dist-info/WHEEL
pynts-0.0.2a1.dist-info/metadata.json
pynts-0.0.2a1.dist-info/top_level.txt
