Metadata-Version: 2.0
Name: pynts
Version: 0.0.2a1
Summary: pynts: Python Naive Time Series: simple utility tools for handling time series data
Home-page: https://github.com/gilbertozp/pynts
Author: Gilberto Pastorello
Author-email: gzpastorello@lbl.gov
License: BSD
Keywords: simple time series tools
Platform: UNKNOWN
Classifier: Development Status :: 2 - Pre-Alpha
Classifier: License :: OSI Approved :: BSD License
Classifier: Intended Audience :: Science/Research
Classifier: Topic :: Scientific/Engineering :: Information Analysis
Classifier: Topic :: Software Development :: Libraries :: Python Modules
Classifier: Programming Language :: Python
Classifier: Programming Language :: Python :: 2
Classifier: Programming Language :: Python :: 2.6
Classifier: Programming Language :: Python :: 2.7
Requires-Dist: numpy
Requires-Dist: matplotlib
Requires-Dist: scipy
Requires-Dist: pytest
Requires-Dist: testfixtures
